{"id":"epzg81heqapv1aqo0p00mv6","title":"Consumer Demand and Cost Factors","desc":"","updated":1740549753093,"created":1740549741279,"custom":{},"fname":"International Trade Network.Economic Growth.Consumer Demand and Cost Factors","type":"note","vault":{"fsPath":".","selfContained":true,"name":"Decoding Complexity"},"contentHash":"24cd22fd0906155ec7993d6f4398cb7b","links":[],"anchors":{"vollrath-et-al-2006":{"type":"header","text":"Vollrath et al., 2006","value":"vollrath-et-al-2006","line":9,"column":0,"depth":3}},"children":[],"parent":"06rwxfvirvxie8d44jmr6ze","data":{}}
