{"id":"nql117sxqchqhvztomyd2to","title":"Complex Networks","nav_order":1,"desc":"","updated":1734840273726,"created":1734710879320,"custom":{"nav_order":1},"fname":"Complex Networks","type":"note","vault":{"fsPath":".","selfContained":true,"name":"Decoding Complexity"},"contentHash":"3557b265f6636df66b0895c21bf7ec54","links":[],"anchors":{"complex-networks":{"type":"header","text":"Complex networks","value":"complex-networks","line":8,"column":0,"depth":2}},"children":[],"parent":"7158c8fk0m4y0idefh3sf12","data":{}}
